bin/unsio_sql3_update_nemorange.pl
bin/unsio_sql3_get_info.pl
bin/unsio_sql3_create_db.pl
bin/unsio_sql3_update_info.pl
include/nemo/io_nemo_data_f.h
include/nemo/getparam.h
include/nemo/filesecret.h
include/nemo/filefn.h
include/nemo/mathfns.h
include/nemo/storyio.h
include/nemo/nemo.h
include/nemo/stdinc.h
include/nemo/version.h
include/nemo/vectmath.h
include/nemo/flags_data.h
include/nemo/io_init.h
include/nemo/io_get_put.h
include/nemo/cpgplot.h
include/nemo/config.h
include/nemo/snode.h
include/nemo/io_nemo_tools.h
include/nemo/maxsizes.h
include/nemo/options.h
include/nemo/maxio.h
include/nemo/parameters.h
include/nemo/extstring.h
include/nemo/gipsyc.h
include/nemo/history.h
include/nemo/history_data_f.h
include/nemo/filestruct.h
include/nemo/check_file.h
include/nemo/io_nemo_data.h
include/nemo/table.h
include/nemo/story.h
include/nemo/get_data_wrapper.h
include/nemo/io_nemo_f.h
include/nemo/command.h
include/nemo/io_get_put_f.h
include/nemo/history_data.h
include/nemo/storyq.h
include/nemo/strlib.h
include/nemo/io_nemo.h
include/nemo/memio.h
include/nemo/snapshot/put_snapshot.c
include/nemo/snapshot/get_snap-old.c
include/nemo/snapshot/put_snap.c
include/nemo/snapshot/barebody.h
include/nemo/snapshot/sphbody.h
include/nemo/snapshot/myput_snap.c
include/nemo/snapshot/body.h
include/nemo/snapshot/myget_snap.c
include/nemo/snapshot/get_snap.c
include/nemo/snapshot/get_snap-ran.c
include/nemo/snapshot/mybody.h
include/nemo/snapshot/put_snap-ran.c
include/nemo/snapshot/stdbody.h
include/nemo/snapshot/put_snap-old.c
include/nemo/snapshot/get_snapshot.c
include/nemo/snapshot/snapshot.h
include/nemo/snapshot/units.h
include/uns/version.h
include/uns/ctools.h
include/uns/userselection.h
include/uns/unsdebug.h
include/uns/componentrange.h
include/uns/uns.h
include/uns/snapshotinterface.h
unsio/version.py
unsio/_py_unsio.cpython-313-darwin.so
unsio/__init__.py
unsio/libunsio.dylib
unsio/input.py
unsio-1.0.2.dist-info/RECORD
unsio-1.0.2.dist-info/WHEEL
unsio-1.0.2.dist-info/entry_points.txt
unsio-1.0.2.dist-info/METADATA
unsio-1.0.2.dist-info/licenses/LICENSE
