Metadata-Version: 2.1
Name: unsio
Version: 1.0.2
Summary: A python wrapper to unsio
Keywords: astrophysics,computing
Author-Email: Jean-Charles Lambert <Jean-Charles.Lambert@lam.fr>
License: UNSIO - Copyright © Jean-Charles LAMBERT 2008-2025
Classifier: Intended Audience :: Science/Research
Classifier: Programming Language :: C
Classifier: Programming Language :: C++
Classifier: Programming Language :: Python
Classifier: Programming Language :: Python :: 3.8
Classifier: Programming Language :: Python :: 3.9
Classifier: Programming Language :: Python :: 3.10
Classifier: Programming Language :: Python :: 3.11
Classifier: Programming Language :: Python :: 3.12
Classifier: Programming Language :: Python :: 3.13
Classifier: Topic :: Scientific/Engineering :: Astronomy
Requires-Python: >=3.8
Requires-Dist: numpy
